camacq/VERSION
camacq/__init__.py
camacq/__main__.py
camacq/bootstrap.py
camacq/config.py
camacq/const.py
camacq/control.py
camacq/event.py
camacq/exceptions.py
camacq/image.py
camacq/log.py
camacq/util.py
camacq/data/__init__.py
camacq/data/config.yml
camacq/helper/__init__.py
camacq/helper/template.py
camacq/plugins/__init__.py
camacq/plugins/rename_image.py
camacq/plugins/api/__init__.py
camacq/plugins/automations/__init__.py
camacq/plugins/automations/event.py
camacq/plugins/leica/__init__.py
camacq/plugins/leica/command.py
camacq/plugins/leica/helper.py
camacq/plugins/leica/sample.py
camacq/plugins/sample/__init__.py
camacq-0.8.0.dist-info/LICENSE
camacq-0.8.0.dist-info/METADATA
camacq-0.8.0.dist-info/WHEEL
camacq-0.8.0.dist-info/entry_points.txt
camacq-0.8.0.dist-info/top_level.txt
camacq-0.8.0.dist-info/RECORD
