Metadata-Version: 2.1
Name: camacq
Version: 0.8.0
Summary: Control microscope through client server program.
Home-page: https://github.com/CellProfiling/cam_acq
Download-URL: https://github.com/CellProfiling/cam_acq/archive/master.zip
Author: Martin Hjelmare
Author-email: marhje52@gmail.com
License: Apache-2.0
Classifier: Development Status :: 3 - Alpha
Classifier: Intended Audience :: Science/Research
Classifier: Topic :: Scientific/Engineering :: Interface Engine/Protocol Translator
Classifier: License :: OSI Approved :: Apache Software License
Classifier: Programming Language :: Python :: 3.10
Classifier: Programming Language :: Python :: 3.11
Classifier: Programming Language :: Python :: 3.12
Classifier: Programming Language :: Python :: 3.13
Requires-Python: >=3.10
License-File: LICENSE
Requires-Dist: async_timeout
Requires-Dist: colorlog
Requires-Dist: jinja2
Requires-Dist: leicacam>=0.4.0
Requires-Dist: leicaimage
Requires-Dist: numpy
Requires-Dist: ruamel.yaml>=0.15
Requires-Dist: tifffile
Requires-Dist: voluptuous
Requires-Dist: xmltodict
